{"slug":"sirkuler-21-129-8433","reference":"Sirkuler_21_129","gazette":"GGM","title":"16 Seri Nolu Tebliğ Kapsamında Düzeltme Talepleri","date":"09 Şubat 2021","bodyHtml":"<p>Rejim beyanının belgelerinde kayıtlı miktarlara göre yapıldığı 16 Seri No.lu Gümrük Genel Tebliği ( Gümrük İşlemleri) kapsamı eşyanın ithalat işlemlerindeki miktar farklılıklarına ilişkin düzeltme taleplerinde usulsüzlük cezası uygulanmaması gerekmektedir.</p><p>İlgili Tebliğ özelliği nedeniyle geçici depolama yerleri ve antrepoya alınmayarak, gümrüğün gözetimi altında sahibine teslim edilecek eşyanın  (<span>supalan-taşıt üstü</span>)  ithalat işlemlerini düzenlemektedir.</p><p>Konuya ilişkin yazı için <a  href=\"https://files.igmd.org.tr/doc/9022021-110727_16-seri-nolu-teblig-kapsaminda-duzeltme-talepleripdf.pdf\" target=\"_blank\">tıklayınız.</a><span><br></span></p>"}
