{"slug":"sirkuler-21-112-8416","reference":"Sirkuler_21_112","gazette":"OAİB","title":"Filipinler Tarafından İthal Edilen Kanatlı Etleri Hk","date":"04 Şubat 2021","bodyHtml":"<p>02.07 GTİP kodlu “01.05 Pozisyonuna giren kümes hayvanlarının etleri ve yenilen sakatatı (taze, soğutulmuş veya dondurulmuş)” ürünlerin Filipinler'e ithalinde  yüzde 40 yerine  yüzde 5 gümrük vergisi uygulanması 31 Aralık 2022 tarihine kadar  uzatılmıştır.</p><p>Konuya ilişkin yazı için   <a  href=\"http://www.oaib.gov.tr/tr/bulten-2021-1073.html\" target=\"_blank\">tıklayınız.</a></p>"}
